spacy_experimental/__init__.py
spacy_experimental/biaffine_parser/__init__.py
spacy_experimental/biaffine_parser/arc_labeler.cp310-win_amd64.pyd
spacy_experimental/biaffine_parser/arc_labeler.pyx
spacy_experimental/biaffine_parser/arc_predicter.cp310-win_amd64.pyd
spacy_experimental/biaffine_parser/arc_predicter.pyx
spacy_experimental/biaffine_parser/bilinear.py
spacy_experimental/biaffine_parser/eval.py
spacy_experimental/biaffine_parser/mst.cp310-win_amd64.pyd
spacy_experimental/biaffine_parser/mst.pxd
spacy_experimental/biaffine_parser/mst.pyx
spacy_experimental/biaffine_parser/pairwise_bilinear.py
spacy_experimental/biaffine_parser/pytorch_bilinear.py
spacy_experimental/biaffine_parser/pytorch_pairwise_bilinear.py
spacy_experimental/biaffine_parser/tests/__init__.py
spacy_experimental/biaffine_parser/tests/test_arc_labeler.py
spacy_experimental/biaffine_parser/tests/test_arc_predicter.py
spacy_experimental/biaffine_parser/tests/test_mst.py
spacy_experimental/char_tokenizer/__init__.py
spacy_experimental/char_tokenizer/char_ner_tokenizer.cp310-win_amd64.pyd
spacy_experimental/char_tokenizer/char_ner_tokenizer.pyx
spacy_experimental/char_tokenizer/char_pretokenizer.py
spacy_experimental/char_tokenizer/char_tagger_tokenizer.cp310-win_amd64.pyd
spacy_experimental/char_tokenizer/char_tagger_tokenizer.pyx
spacy_experimental/char_tokenizer/scorers.py
spacy_experimental/char_tokenizer/tests/__init__.py
spacy_experimental/char_tokenizer/tests/test_char_tokenizers.py
spacy_experimental/coref/__init__.py
spacy_experimental/coref/coref_component.py
spacy_experimental/coref/coref_model.py
spacy_experimental/coref/coref_scorer.py
spacy_experimental/coref/coref_util.py
spacy_experimental/coref/pytorch_coref_model.py
spacy_experimental/coref/pytorch_span_resolver_model.py
spacy_experimental/coref/span_resolver_component.py
spacy_experimental/coref/span_resolver_model.py
spacy_experimental/coref/tests/__init__.py
spacy_experimental/coref/tests/test_coref.py
spacy_experimental-0.6.4.dist-info/LICENSE
spacy_experimental-0.6.4.dist-info/METADATA
spacy_experimental-0.6.4.dist-info/WHEEL
spacy_experimental-0.6.4.dist-info/entry_points.txt
spacy_experimental-0.6.4.dist-info/top_level.txt
spacy_experimental-0.6.4.dist-info/RECORD
