Metadata-Version: 2.1
Name: spacy-experimental
Version: 0.6.4
Summary: Cutting-edge experimental spaCy components and features
Home-page: https://github.com/explosion/spacy-experimental
Author: Explosion
Author-email: contact@explosion.ai
License: MIT
Requires-Python: >=3.6
License-File: LICENSE
Requires-Dist: spacy<3.8.0,>=3.3.0
Requires-Dist: numpy>=1.15.0; python_version < "3.9"
Requires-Dist: numpy>=1.19.0; python_version >= "3.9"
Provides-Extra: torch
Requires-Dist: torch>=1.5.0; extra == "torch"
